LICENSE
MANIFEST.in
README.md
README.rst
setup.py
flexion/__init__.py
flexion/flexion.py
flexion/map_smor_conllu.py
flexion.egg-info/PKG-INFO
flexion.egg-info/SOURCES.txt
flexion.egg-info/dependency_links.txt
flexion.egg-info/requires.txt
flexion.egg-info/top_level.txt
flexion.egg-info/zip-safe
scripts/download_transducer.py
test/__init__.py
test/test_map.py
test/test_replace.py