Metadata-Version: 2.1
Name: flexion
Version: 0.1.2
Summary: Applying declination and conjugation rules to lemmata.
Home-page: http://github.com/ulf/flexion
Author: Ulf Hamster
Author-email: 554c46@gmail.com
License: Apache License 2.0
Platform: UNKNOWN
Requires-Python: >=3.6
License-File: LICENSE
